setup.py
CherwellAPI/BusinessObjects.py
CherwellAPI/Cache.py
CherwellAPI/CherwellClient.py
CherwellAPI/CherwellCredentials.py
CherwellAPI/Filter.py
CherwellAPI/Token.py
CherwellAPI/__init__.py
Examples/Create_CI_With_Dynamic_Attributes.py
Examples/Example_Cache.py
Examples/Example_CreateEncryptedCredentials.py
Examples/Example_CreateIncident.py
Examples/Example_CreateIncident_with_BusinessObject.py
Examples/Example_Create_New_Custom_Business_Object.py
Examples/Example_Delete_Incident_with_BusinessObjects.py
Examples/Example_GetInternalName.py
Examples/Example_Get_Summary.py
Examples/Example_Get_Template.py
Examples/Example_RunSavedSearch.py
Examples/Example_Searches.py
Examples/Example_Searches_with_BusinessObjects.py
Examples/Example_Token Usage.py
Examples/Example_Update_Incident_with_BusinessObjects.py
Examples/__init__.py
LSVcherwellAPI-1.3.9.2.dist-info/METADATA
LSVcherwellAPI-1.3.9.2.dist-info/WHEEL
LSVcherwellAPI-1.3.9.2.dist-info/top_level.txt
LSVcherwellAPI-1.3.9.2.dist-info/RECORD
