Metadata-Version: 2.1
Name: LSVcherwellAPI
Version: 1.3.9.2
Summary: A Python library wrapper, abstracting the Cherwell REST API
Author-email: David Graupner <david.graupner@streamlinepartners.com.au>, Aaron Cohee <aaron.cohee@streamlinepartners.com.au>, Marty Leaman <marty.leaman@streamlinepartners.com.au>, Brandon Wittenburg <brandon.wittenburg@usablelife.com>
Project-URL: Homepage, https://github.com/bwittenburg/CherwellAPI
Project-URL: Issues, https://github.com/bwittenburg/CherwellAPI/issues
Classifier: Programming Language :: Python :: 2.6
Classifier: Programming Language :: Python :: 2.7
Classifier: Programming Language :: Python :: 3.4
Classifier: Programming Language :: Python :: 3.5
Classifier: Programming Language :: Python :: 3.6
Classifier: Programming Language :: Python :: 3.7
Classifier: Programming Language :: Python :: 3.8
Classifier: Programming Language :: Python :: 3.9
Classifier: License :: OSI Approved :: MIT License
Classifier: Operating System :: OS Independent
